rdf_fastapi_utils/__init__.py
rdf_fastapi_utils/models.py
rdf_fastapi_utils/tests/__init__.py
rdf_fastapi_utils/tests/baseclass_test.py
rdf_fastapi_utils/tests/test_data.json
rdf_fastapi_utils/tests/test_data_events.json
rdf_fastapi_utils-0.1.3.dist-info/WHEEL
rdf_fastapi_utils-0.1.3.dist-info/METADATA
rdf_fastapi_utils-0.1.3.dist-info/RECORD
