Metadata-Version: 2.1
Name: rdf-fastapi-utils
Version: 0.1.3
Summary: Utils package for interacting with SPARQL endpoint via FastAPI
License: MIT
Author: Matthias Schlögl
Author-email: matthias.schloegl@oeaw.ac.at
Requires-Python: >=3.10,<4.0
Classifier: License :: OSI Approved :: MIT License
Classifier: Programming Language :: Python :: 3
Classifier: Programming Language :: Python :: 3.10
Classifier: Programming Language :: Python :: 3.11
Requires-Dist: pydantic (>=1.10.2,<2.0.0)
Requires-Dist: rdflib (>=6.2.0,<7.0.0)
